Workbook
Name _3.0_1.5__0.10_0.10: #REF!
Name _Order1: 255
Name _Order2: 255
Name A2A3零星: #N/A
Name A2A3外墙: #N/A
Name A2A3阳台: #N/A
Name AAA_DOCTOPS: "AAA_SET"
Name AAA_duser: "OFF"
Name AAB_Addin5: "AAB_Description for addin 5,Description for addin 5,Description for addin 5,Description for addin 5,Description for addin 5,Description for addin 5"
Name dss: #N/A
Name HWSheet: 1
Name louti: B
Name louti: B
Name m: "Evaluate+室外园林给排水工程!$E$6"
Name Print_Area_MI: #REF!
Name TestAdd: "Test RefersTo1"
Name 八: '[2]8'!$B$6:$G$9
Name 出: #REF!
Name 二: '[2]2'!$B$6:$G$13
Name 汇率: #REF!
Name 六: '[2]6'!$B$6:$G$8
Name 面积合计: '[2]面积合计（藏）'!$B$5:$H$88
Name 模板计算公式: B
Name 模板计算公式: B
Name 内墙、天花、地面: B
Name 内墙、天花、地面: B
Name 七: '[2]7'!$B$6:$G$15
Name 三: '[2]3'!$B$6:$G$9
Name 身材列: #REF!
Name 生产列1: #REF!
Name 生产列100: #REF!
Name 生产列11: #REF!
Name 生产列15: #REF!
Name 生产列16: #REF!
Name 生产列17: #REF!
Name 生产列19: #REF!
Name 生产列2: #REF!
Name 生产列20: #REF!
Name 生产列25: #REF!
Name 生产列3: #REF!
Name 生产列4: #REF!
Name 生产列5: #REF!
Name 生产列6: #REF!
Name 生产列7: #REF!
Name 生产列8: #REF!
Name 生产列9: #REF!
Name 生产期: #REF!
Name 生产期1: #REF!
Name 生产期11: #REF!
Name 生产期15: #REF!
Name 生产期16: #REF!
Name 生产期17: #REF!
Name 生产期19: #REF!
Name 生产期2: #REF!
Name 生产期20: #REF!
Name 生产期3: #REF!
Name 生产期4: #REF!
Name 生产期5: #REF!
Name 生产期6: #REF!
Name 生产期7: #REF!

Sheet 区采 表4.1 综合单价清单
A1: ='[3]表1 招标封面'!A3 -> 融创西南区域集团2019-2020年造价咨询区采招标【仅限重庆、四川、广西、云南、贵州】
A2: 分部分项全费用综合单价清单
A4: 序号 | B4: 项目名称 | C4: 计算内容及计算公式 | D4: 造价咨询费用计算规则 | E4: 单位 | F4: 工程量 | G4: 综合单价1 | H4: 综合单价2 | I4: 合价1 | J4: 合价2 | K4: 综合单价组成 | N4: 价格来源 | O4: 备注
G5: 不含增值税 | H5: 含增值税 | K5: 直接工程费 | L5: 企业管理费、利润、规费等 Ⓐ % | M5: 增值税专用发票税额 Ⓑ %
I6: 不含增值税 | J6: 含增值税 | K6: 直接工程费用
L8: 0.14 | M8: 0.06
F9: A | G9: B1=a+b | H9: B2=a+b+c | I9: C1=A*B1 | J9: C2=A*B2 | K9: a | L9: b=a*Ⓐ% | M9: c=（a+b）*Ⓑ%
A11: 一 | B11: 施工图预算编制及核对 | I11: =SUBTOTAL(9,I12:I25) -> 469103.44 | J11: =SUBTOTAL(9,J12:J25) -> 497249.65 | P11: =+J11*0.4 -> 198899.86
A12: 1 | B12: 小高层、高层、超高层、办公楼和公寓（层数F＞8）、除别墅外下方裙房商业（均不分层高、层数）及相应地下室，高层区车库 | C12: 计算内容：基础结算，散水以内（含散水、排水沟）的主体结构工程、砌体工程、装饰工程（不含二次设计）、楼地面工程、保温工程、外墙饰面（以下单独委托内容以外的部分）、屋面工程、防水工程、给水排水工程、强弱电工程、防雷工程等施工图包干预算编制及核对。具体计算方式详见甲方与总包单位的战略协议。 | D12: 按包干固定综合单价*面积计算，面积按该楼栋施工图预算的建筑面积（即按《中华人民共和国国家标准建筑工程建筑面积计算规范》（GB/T50353-2013）以建筑面积计算，架空层部分已按满堂式钢管支架计算其脚手架费用,不再计算建筑面积，扣除钢楼（屋）面、钛锌板楼（屋）面等专业分包所涉及的面积。）计算。 | E12: m2 | F12: =+工程量计算式!C23-工程量计算式!C21 -> 197402.06 | G12: =K12+L12 -> 2.337 | H12: =K12+L12+M12 -> 2.47722 | I12: =$F12*G12 -> 461328.61 | J12: =$F12*H12 -> 489008.33 | K12: 2.05 | L12: =K12*$L$8 -> 0.287 | M12: =(K12+L12)*$M$8 -> 0.14022
A13: 2 | B13: 小高层、高层、超高层、办公楼和公寓（层数F＞8）、独立商业、除别墅外下方裙房商业（均不分层高、层数）相同楼栋 | E13: m2 | G13: =K13+L13 -> 1.1229 | H13: =K13+L13+M13 -> 1.190274 | I13: =$F13*G13 -> 0 | J13: =$F13*H13 -> 0 | K13: 0.985 | L13: =K13*$L$8 -> 0.1379 | M13: =(K13+L13)*$M$8 -> 0.067374
A14: 3 | B14: 别墅（不分产品类型）、叠拼、学校、幼儿园、别墅下裙房商业、会所（公众场馆）、售楼部（层数F≤8）、门房、岗亭及相应地下室，别墅区车库 | E14: m2 | G14: =K14+L14 -> 4.674 | H14: =K14+L14+M14 -> 4.95444 | I14: =$F14*G14 -> 0 | J14: =$F14*H14 -> 0 | K14: 4.1 | L14: =K14*$L$8 -> 0.574 | M14: =(K14+L14)*$M$8 -> 0.28044
A15: 4 | B15: 别墅（不分产品类型）、叠拼、学校、幼儿园、别墅下裙房商业、会所（公众场馆）、售楼部（层数F≤8）、门房、岗亭相同楼栋 | E15: m2 | G15: =K15+L15 -> 2.1546 | H15: =K15+L15+M15 -> 2.283876 | I15: =$F15*G15 -> 0 | J15: =$F15*H15 -> 0 | K15: 1.89 | L15: =K15*$L$8 -> 0.2646 | M15: =(K15+L15)*$M$8 -> 0.129276
A16: 5 | B16: 花园洋房（5≤层数F≤8）及相应地下室、办公楼和公寓(层数F≤8)、洋房区车库 | E16: m2 | G16: =K16+L16 -> 2.8044 | H16: =K16+L16+M16 -> 2.972664 | I16: =$F16*G16 -> 0 | J16: =$F16*H16 -> 0 | K16: 2.46 | L16: =K16*$L$8 -> 0.3444 | M16: =(K16+L16)*$M$8 -> 0.168264
A17: 6 | B17: 花园洋房（5≤层数F≤8）、办公楼和公寓(层数F≤8)相同楼栋 | E17: m2 | G17: =K17+L17 -> 1.2198 | H17: =K17+L17+M17 -> 1.292988 | I17: =$F17*G17 -> 0 | J17: =$F17*H17 -> 0 | K17: 1.07 | L17: =K17*$L$8 -> 0.1498 | M17: =(K17+L17)*$M$8 -> 0.073188
A18: 7 | B18: 独立商业 | E18: m2 | F18: =+工程量计算式!C21 -> 1663.42 | G18: =K18+L18 -> 4.674 | H18: =K18+L18+M18 -> 4.95444 | I18: =$F18*G18 -> 7774.8251 | J18: =$F18*H18 -> 8241.3146 | K18: 4.1 | L18: =K18*$L$8 -> 0.574 | M18: =(K18+L18)*$M$8 -> 0.28044
A19: 8 | B19: 独立商业相同楼栋 | E19: m2 | G19: =K19+L19 -> 2.1546 | H19: =K19+L19+M19 -> 2.283876 | I19: =$F19*G19 -> 0 | J19: =$F19*H19 -> 0 | K19: 1.89 | L19: =K19*$L$8 -> 0.2646 | M19: =(K19+L19)*$M$8 -> 0.129276
A20: 9 | B20: 土建分包区采 | C20: 1、按施工图纸、事务所工作任务通知书范围要求计算，具体计算方式详见甲方与分包单位的战略协议； 2、包括外檐一体化、门窗、管网、防火门、入户门、屋面系统等等所有除总包以外的区采项目。 | D20: 1、一般情况按甲方与总包（或分包）单位签定合同金额计算； 2、若计算范围内有涉及相同户型、相同楼栋、相同楼层等相同设计内容时，只计算一次咨询费，不重复计算，但出具的咨询报告应包含所有的“二次设计内容（或分包工程）”的内容。 | E20: 元 | G20: =K20+L20 -> 0.002451 | H20: =K20+L20+M20 -> 0.00259806 | I20: =$F20*G20 -> 0 | J20: =$F20*H20 -> 0 | K20: 0.00215 | L20: =K20*$L$8 -> 0.000301 | M20: =(K20+L20)*$M$8 -> 0.00014706
A21: 10 | B21: 安装分包区采 | C21: 1、按施工图纸、事务所工作任务通知书范围要求计算，具体计算方式详见甲方与总包单位、分包单位的战略协议。 2、包括智能化、下户线工程、消防工程、专配出线、中央空调工程、天沟及落水管等等所有安装除总包以外的区采项目。 | D21: 1、一般情况按甲方与总包（或分包）单位签定合同金额计算； 2、若计算范围内有涉及相同户型、相同楼栋、相同楼层等相同设计内容时，只计算一次咨询费，不重复计算，但出具的咨询报告应包含所有的“二次设计内容（或分包工程）”的内容。 | E21: 元 | G21: =K21+L21 -> 0.002622 | H21: =K21+L21+M21 -> 0.00277932 | I21: =$F21*G21 -> 0 | J21: =$F21*H21 -> 0 | K21: 0.0023 | L21: =K21*$L$8 -> 0.000322 | M21: =(K21+L21)*$M$8 -> 0.00015732
A22: 11 | B22: 精装区采 | C22: 1、按施工图纸、事务所工作任务通知书范围要求计算，具体计算方式详见甲方与分包单位的战略协议。 2、包含大堂、会所、样板房、公共部位、电梯前室、成品房装饰装修等精装修区采项目。 | D22: 1、一般情况下按甲方与分包单位签定合同金额计算； 2、若计算范围内有涉及相同户型、相同楼栋、相同楼层等相同设计内容时，只计算一次咨询费，不重复计算，但出具的咨询报告应包含所有的“二次设计内容（或分包工程）”的内容。 | E22: 元 | G22: =K22+L22 -> 0.00285 | H22: =K22+L22+M22 -> 0.003021 | I22: =$F22*G22 -> 0 | J22: =$F22*H22 -> 0 | K22: 0.0025 | L22: =K22*$L$8 -> 0.00035 | M22: =(K22+L22)*$M$8 -> 0.000171
A23: 12 | B23: 景观区采 | C23: 1、按施工图纸、事务所工作任务通知书范围要求计算，具体计算方式详见甲方与分包单位的战略协议。 2、包含景观工程、艺术廊架、景观铁艺、雕塑等等景观区采项目。 | D23: 1、一般情况按甲方与总包（或分包）单位签定合同金额计算； 2、若计算范围内有涉及相同户型、相同楼栋、相同楼层等相同设计内容时，只计算一次咨询费，不重复计算，但出具的咨询报告应包含所有的“二次设计内容（或分包工程）”的内容。 | E23: 元 | G23: =K23+L23 -> 0.002622 | H23: =K23+L23+M23 -> 0.00277932 | I23: =$F23*G23 -> 0 | J23: =$F23*H23 -> 0 | K23: 0.0023 | L23: =K23*$L$8 -> 0.000322 | M23: =(K23+L23)*$M$8 -> 0.00015732
A24: 13 | B24: 市政工程 | C24: 1、按施工图纸、事务所工作任务通知书范围要求计算，具体计算方式详见甲方与分包单位的战略协议。 2、市政项目。 | D24: 1、一般情况按甲方与总包（或分包）单位签定合同金额计算； 2、若计算范围内有涉及相同户型、相同楼栋、相同楼层等相同设计内容时，只计算一次咨询费，不重复计算，但出具的咨询报告应包含所有的“二次设计内容（或分包工程）”的内容。 | E24: 元 | G24: =K24+L24 -> 0.00228 | H24: =K24+L24+M24 -> 0.0024168 | I24: =$F24*G24 -> 0 | J24: =$F24*H24 -> 0 | K24: 0.002 | L24: =K24*$L$8 -> 0.00028 | M24: =(K24+L24)*$M$8 -> 0.0001368
A26: 二 | B26: 全过程造价服务 | I26: =SUBTOTAL(9,I27:I34) -> 0 | J26: =SUBTOTAL(9,J27:J34) -> 0
A27: 14 | B27: 小高层（9≤层数F≤18）、高层（18＜层数F≤33）、超高层、办公楼和公寓(层数F＞8)、除别墅外下方裙房商业及相应地下室，高层区车库 | C27: 具体内容详见《全过程造价咨询合同》 | D27: 1、按包干固定综合单价*面积计算，面积按该楼栋的施工图预算的建筑面积（按《中华人民共和国国家标准建筑工程建筑面积计算规范》（GB/T50353-2013）中的建筑面积计算，架空层部分已按满堂式钢管支架计算其脚手架费用,不再计算建筑面积，扣除钢楼（屋）面、钛锌板楼（屋）面等专业分包所涉及的面积）计算。 2、异地样板房随各业态计价。 | E27: m2 | G27: =K27+L27 -> 8.322 | H27: =K27+L27+M27 -> 8.82132 | I27: =$F27*G27 -> 0 | J27: =$F27*H27 -> 0 | K27: 7.3 | L27: =K27*$L$8 -> 1.022 | M27: =(K27+L27)*$M$8 -> 0.49932
A28: 15 | B28: 别墅、别墅下裙房商业、学校、幼儿园、叠拼、会所（公众场馆）、门房、岗亭及相应地下室、售楼部（层数F≤8），别墅区车库 | C28: 具体内容详见《全过程造价咨询合同》 | D28: 1、按包干固定综合单价*面积计算，面积按该楼栋的施工图预算的建筑面积（按《中华人民共和国国家标准建筑工程建筑面积计算规范》（GB/T50353-2013）中的建筑面积计算，架空层部分已按满堂式钢管支架计算其脚手架费用,不再计算建筑面积，扣除钢楼（屋）面、钛锌板楼（屋）面等专业分包所涉及的面积）计算。 2、异地样板房随各业态计价。 | E28: m2 | G28: =K28+L28 -> 13.0929 | H28: =K28+L28+M28 -> 13.878474 | I28: =$F28*G28 -> 0 | J28: =$F28*H28 -> 0 | K28: 11.485 | L28: =K28*$L$8 -> 1.6079 | M28: =(K28+L28)*$M$8 -> 0.785574
A29: 16 | B29: 融创桃源系列项目（新增） | C29: 具体内容详见《全过程造价咨询合同》 | D29: 1、按包干固定综合单价*面积计算，面积按该楼栋的施工图预算的建筑面积（按《中华人民共和国国家标准建筑工程建筑面积计算规范》（GB/T50353-2013）中的建筑面积计算，架空层部分已按满堂式钢管支架计算其脚手架费用,不再计算建筑面积，扣除钢楼（屋）面、钛锌板楼（屋）面等专业分包所涉及的面积）计算。 2、异地样板房随各业态计价。 | E29: m2 | G29: =K29+L29 -> 19.38 | H29: =K29+L29+M29 -> 20.5428 | I29: =$F29*G29 -> 0 | J29: =$F29*H29 -> 0 | K29: 17 | L29: =K29*$L$8 -> 2.38 | M29: =(K29+L29)*$M$8 -> 1.1628
A30: 17 | B30: 花园洋房（5≤层数F≤8）及相应地下室、办公楼和公寓(层数F≤8)，洋房区车库 | C30: 具体内容详见《全过程造价咨询合同》 | D30: 1、按包干固定综合单价*面积计算，面积按该楼栋的施工图预算的建筑面积（按《中华人民共和国国家标准建筑工程建筑面积计算规范》（GB/T50353-2013）中的建筑面积计算，架空层部分已按满堂式钢管支架计算其脚手架费用,不再计算建筑面积，扣除钢楼（屋）面、钛锌板楼（屋）面等专业分包所涉及的面积）计算。 2、异地样板房随各业态计价。 | E30: m2 | G30: =K30+L30 -> 10.2828 | H30: =K30+L30+M30 -> 10.899768 | I30: =$F30*G30 -> 0 | J30: =$F30*H30 -> 0 | K30: 9.02 | L30: =K30*$L$8 -> 1.2628 | M30: =(K30+L30)*$M$8 -> 0.616968
A31: 18 | B31: 独立商业 | C31: 具体内容详见《全过程造价咨询合同》 | D31: 1、按包干固定综合单价*面积计算，面积按该楼栋的施工图预算的建筑面积（按《中华人民共和国国家标准建筑工程建筑面积计算规范》（GB/T50353-2013）中的建筑面积计算，架空层部分已按满堂式钢管支架计算其脚手架费用,不再计算建筑面积，扣除钢楼（屋）面、钛锌板楼（屋）面等专业分包所涉及的面积）计算。 2、异地样板房随各业态计价。 | E31: m2 | G31: =K31+L31 -> 13.0929 | H31: =K31+L31+M31 -> 13.878474 | I31: =$F31*G31 -> 0 | J31: =$F31*H31 -> 0 | K31: 11.485 | L31: =K31*$L$8 -> 1.6079 | M31: =(K31+L31)*$M$8 -> 0.785574
A32: 19 | B32: 成品房交付标准楼栋补偿费用（±0.00以上部分） | C32: 具体内容详见《全过程造价咨询合同》 | D32: 1、如部分楼栋为成品房交付标准，则计算该楼栋成品房交付标准楼栋补偿费用； 2、按包干固定综合单价*面积计算，面积按成品房装修楼地面面积计算。 | E32: m2 | G32: =K32+L32 -> 1.8696 | H32: =K32+L32+M32 -> 1.981776 | I32: =$F32*G32 -> 0 | J32: =$F32*H32 -> 0 | K32: 1.64 | L32: =K32*$L$8 -> 0.2296 | M32: =(K32+L32)*$M$8 -> 0.112176
A33: 20 | B33: 快维工程 | C33: 工作内容： 1、勘察现场、收方； 2、根据收方资料及图纸进行计算； 3、解决争议问题等等。 | D33: 1、以合同额绝对值总和作为计费基数；2、本快维清单适用于该工程竣备交付后产生的快维工作，施工过程中的快维工作内容已包含在全过程造价咨询清单中，不单独计算。 | E33: 元 | G33: =K33+L33 -> 0.0056088 | H33: =K33+L33+M33 -> 0.005945328 | I33: =$F33*G33 -> 0 | J33: =$F33*H33 -> 0 | K33: 0.00492 | L33: =K33*$L$8 -> 0.0006888 | M33: =(K33+L33)*$M$8 -> 0.000336528 | O33: 综合单价为百分比
A35: 三 | B35: 结算编制及审核 | I35: =SUBTOTAL(9,I36:I44) -> 0 | J35: =SUBTOTAL(9,J36:J44) -> 0
A36: 21 | B36: 总包工程 | C36: 工作内容： 1、对现场进行复查，合同内未施工部分需要向甲方提出； 2、可调价部分按核价及图纸进行结算； 3、材料价差部分视规定进行调差； 4、变更签证部分进行结算； 5、争议部分进行解决。 | D36: 1、变更签证部分:结算额绝对值总和作为计费基数 2、合同暂定工程量部分：按包干预算合同内暂定工程量相应清单项结算金额合计作为计费基数。 | E36: 元 | G36: =K36+L36 -> 0.003762 | H36: =K36+L36+M36 -> 0.00398772 | I36: =$F36*G36 -> 0 | J36: =$F36*H36 -> 0 | K36: 0.0033 | L36: =K36*$L$8 -> 0.000462 | M36: =(K36+L36)*$M$8 -> 0.00022572 | O36: 综合单价为百分比
D37: 3、可调材料价差部分：按包干预算合同内暂定综合单价(办理结算时需调差)部分结算后各清单项增减金额绝对值总和作为计费基数 | E37: 元 | G37: =K37+L37 -> 0.001938 | H37: =K37+L37+M37 -> 0.00205428 | I37: =$F37*G37 -> 0 | J37: =$F37*H37 -> 0 | K37: 0.0017 | L37: =K37*$L$8 -> 0.000238 | M37: =(K37+L37)*$M$8 -> 0.00011628 | O37: 综合单价为百分比
A38: 22 | B38: 精装工程 | C38: 工作内容： 1、对现场进行复查，合同内未施工部分需要向甲方提出； 2、可调价部分按核价及图纸进行结算； 3、材料价差部分视规定进行调差； 4、变更签证部分进行结算； 5、争议部分进行解决。 | D38: 1、变更签证部分:结算额绝对值总和作为计费基数 2、合同暂定工程量部分：按包干预算合同内暂定工程量相应清单项结算金额合计作为计费基数。 | E38: 元 | G38: =K38+L38 -> 0.003762 | H38: =K38+L38+M38 -> 0.00398772 | I38: =$F38*G38 -> 0 | J38: =$F38*H38 -> 0 | K38: 0.0033 | L38: =K38*$L$8 -> 0.000462 | M38: =(K38+L38)*$M$8 -> 0.00022572 | O38: 综合单价为百分比
D39: 3、可调材料价差部分：按包干预算合同内暂定综合单价(办理结算时需调差)部分结算后各清单项增减金额绝对值总和作为计费基数。 | E39: 元 | G39: =K39+L39 -> 0.001938 | H39: =K39+L39+M39 -> 0.00205428 | I39: =$F39*G39 -> 0 | J39: =$F39*H39 -> 0 | K39: 0.0017 | L39: =K39*$L$8 -> 0.000238 | M39: =(K39+L39)*$M$8 -> 0.00011628 | O39: 综合单价为百分比
A40: 23 | B40: 景观工程 | C40: 工作内容： 1、对现场进行复查，合同内未施工部分需要向甲方提出； 2、可调价部分按核价及图纸进行结算； 3、材料价差部分视规定进行调差； 4、变更签证部分进行结算； 5、争议部分进行解决。 | D40: 1、变更签证部分:结算额绝对值总和作为计费基数 2、合同暂定工程量部分：按包干预算合同内暂定工程量相应清单项结算金额合计作为计费基数。 | E40: 元 | G40: =K40+L40 -> 0.003762 | H40: =K40+L40+M40 -> 0.00398772 | I40: =$F40*G40 -> 0 | J40: =$F40*H40 -> 0 | K40: 0.0033 | L40: =K40*$L$8 -> 0.000462 | M40: =(K40+L40)*$M$8 -> 0.00022572 | O40: 综合单价为百分比
D41: 3、可调材料价差部分：按包干预算合同内暂定综合单价(办理结算时需调差)部分结算后各清单项增减金额绝对值总和作为计费基数。 | E41: 元 | G41: =K41+L41 -> 0.001938 | H41: =K41+L41+M41 -> 0.00205428 | I41: =$F41*G41 -> 0 | J41: =$F41*H41 -> 0 | K41: 0.0017 | L41: =K41*$L$8 -> 0.000238 | M41: =(K41+L41)*$M$8 -> 0.00011628 | O41: 综合单价为百分比
A42: 24 | B42: 管网挡墙工程 | C42: 工作内容： 1、对现场进行复查，合同内未施工部分需要向甲方提出； 2、可调价部分按核价及图纸进行结算； 3、材料价差部分视规定进行调差； 4、变更签证部分进行结算； 5、争议部分进行解决。 | D42: 1、变更签证部分:结算额绝对值总和作为计费基数； 2、合同暂定工程量部分：按包干预算合同内暂定工程量相应清单项结算金额合计作为计费基数。 | E42: 元 | G42: =K42+L42 -> 0.003762 | H42: =K42+L42+M42 -> 0.00398772 | I42: =$F42*G42 -> 0 | J42: =$F42*H42 -> 0 | K42: 0.0033 | L42: =K42*$L$8 -> 0.000462 | M42: =(K42+L42)*$M$8 -> 0.00022572 | O42: 综合单价为百分比
D43: 3、可调材料价差部分：按包干预算合同内暂定综合单价(办理结算时需调差)部分结算后各清单项增减金额绝对值总和作为计费基数。 | E43: 元 | G43: =K43+L43 -> 0.001938 | H43: =K43+L43+M43 -> 0.00205428 | I43: =$F43*G43 -> 0 | J43: =$F43*H43 -> 0 | K43: 0.0017 | L43: =K43*$L$8 -> 0.000238 | M43: =(K43+L43)*$M$8 -> 0.00011628 | O43: 综合单价为百分比
B45: 本工程造价合计： | I45: =SUBTOTAL(9,I10:I43) -> 469103.44 | J45: =SUBTOTAL(9,J10:J43) -> 497249.65
A47: 备注： 1、小高层、高层、超高层、办公楼、独立商业、除别墅外下方裙房商业（均不分层高、层数）相同楼栋及别墅（不分产品类型）、花园洋房、叠拼、学校、幼儿园、别墅下裙房商业、会所、门房、岗亭相同楼栋主要是针对具有多栋相同楼栋的建筑物时，其中一栋楼按基本费单价（第1项、3项、5项或第7项）计算咨询费，其它楼栋按相同楼栋单价（第2项、4项、6项或第8项）计算咨询费。相同楼栋判断标准：按建筑图纸是否相同进行判断（按楼栋编号命名是否在同一张图纸上，如有局部差异仍按相同楼栋执行），如高层1#楼与高层2#楼3~26层建筑图相同，则1#楼3~26层咨询费按以上清单第1项进行计算，2#楼3~26层按以上清单第2项相同楼栋单价计算咨询费。洋房、别墅相同楼栋均参照此例计算咨询费。 2、车库归属按为谁服务进行判断，车库为别墅服务则按别墅区车库、为高层服务则按高层区车库计算咨询费用。 3、施工图预算中“二次设计内容（或分包工程）第9~13项”涉及相同户型、相同楼栋、相同楼层等相同设计内容的只计算相同内容其中一个户型、一个楼栋或一层楼的咨询费，但出具的咨询报告应包含所有的“二次设计内容（或分包工程）”的内容。（例如：2#楼公共部位装修共计26层，该26层装修均相同，计算咨询费时，只计算首层的公共部位装修的咨询费，但咨询报告应包括首层至26层的总造价。） 4、由于设计变更等甲方的原因造成的返工，无论变更一次或多次均补偿一次，且返工的面积需超过本次委托单项工程面积的60%以上。 4.1 施工图预算中以上清单第1~8项由于甲方的原因造成已计算完成的工程量作废而进行的返工、补偿按相应的业态的固定包干单价× 40% ×返工的面积（报百分比）。 4.2 施工图预算中以上清单第9项~13项由于甲方的原因造成已计算完成的工程量作废而进行的返工、补偿按相应的返工范围的工程造价咨询费× 40%。 5、乙方在接受总包土建工程施工图预算第1~8项任务后，若甲方委托的项目后期含有第9~13项、第20~23项的内容，乙方将完全按照甲方的要求完成该条款内容，否则，甲方有权停付已完工程的进度款，并解除造价咨询合同，且乙方应按当期合同总造价的20%向甲方支付违约金。如后期增加结算审核任务（仅限于承接总包预算楼栋的同组团或同分期范围内），乙方亦按照甲方的要求完成该条款内容，否则，甲方有权停付其他承接已完工程的进度款，并解除正在合作的造价咨询合同，且乙方应按正在合作的合同总造价的20%向甲方支付违约金，如未有正在合同的项目，则解除战略合同协议。 6、结算编制及审核的咨询费计费基数计算如下：如某总包工程包干预算合同金额为2000万(其中暂定量清单项合计300万元)，办理结算后总造价3500万(含增项变更签证600万、减项变更签证100万，暂定工程量清单项结算后为500万，合同清单项可调材料调差调增1000万、调减200万)，则计算咨询费时，变更签证部分计费基数：600万（增项变更）+100万（减项变更）＝700万；合同内暂定工程量部分计费基数：500万（暂定工程量清单项结算金额）；可调材料价差部分计费基数：1000万（可调材料调差调增）+200万（可调材料调差调减）＝1200万。精装、景观、管网挡墙工程均参照此例计算咨询费。 7、本合作协议中约定的价格为甲方与乙方签订具体项目《**项目**期工程造价咨询合同》或《全过程造价咨询合同》的定价依据，该区采协议的附件报价清单体系应被认为乙方理解并接受该价款的合理性以及风险，该单价在本协议确定的合作期内不因市场变化而进行任何调整。 8、全过程事务所、复审事务所及三审（抽审）事务所均有权对施工图提出优化建议方案，包含但不限于：新工艺、新技术、新设备、新材料，或根据项目所在地的地方特色、气候特点、政府要求等，若经研发、工程及成本一致认为该方案可采纳并实施，则城市公司二级平台可上报一级平台预结算审核部，对该优化建议进行报备，通过后可对提出该方案相关事务所人员进行奖励，具体金额如下： （1）优化涉及金额20万以上125万（含）以下，奖励优化涉及金额的1%，最高不超过1万元； （2）优化涉及金额125万以上500万（含）以下，奖励优化涉及金额的0.8%，最高不超过2万元； （3）优化涉及金额500万以上，奖励优化涉及金额的0.4%，最高不超过5万元。 9、其他要求详见事务所管理制度。

Sheet 表2 编制说明
A1: ='[3]表1 招标封面'!A3 -> 融创西南区域集团2019-2020年造价咨询区采招标【仅限重庆、四川、广西、云南、贵州】
A2: 编制、填报说明
A4: 一、术语解释:
A5: 1、 | B5: 本清单中“以下” 含本身，“以上”不含本身
A7: 二、清单项适用范围说明：
A8: 1、 | B8: 本清单价格适用于融创中国西南区域公司下的重庆、四川、广西、云南、贵州地区的房地产开发项目。
A9: 2、 | B9: 本清单执行期为：2019年8月1日到2020年12月31日。
A11: 三、计算规则：
A12: 1、 | B12: 详见表4综合单价清单中的备注部分。
A13: 2、 | B13: 全过程事务所中，驻现在人员驻场服务时间超过计划工期2个月以上，则2个月以内视为正常工程合同延期情况，费用不许增加，2个月以上不满3个月的，按照实际驻场天数，以10000元为基数进行折算；若超过2个月，每月增加合同费用10000元。
A14: 3、 | B14: A、预结算复审服务 复审事务所受一级平台预结算审核部（非成熟区域）、二级平台（成熟区域）委托，对非成熟区域城市公司、成熟区域城市公司项目成本提交的预结算造价成果文件进行的审核服务。
A15: 4、 | B15: B、预结算三审(抽审)服务 三审(抽审)事务所受一级平台预结算审核部委托，对城市公司提交的预结算造价成果文件进行的审核服务。
A17: 四、特别说明、填报说明
A18: 1、 | B18: 本清单已经包含了此工程应包含的所有费用，清单中没有列明的项目表示已经综合考虑到的清单当中。
A19: 2、 | B19: 各单位提供的发票为“增值税专用发票”，且需符合工程合同中的相关要求。
A20: 3、 | B20: 本清单中“增值税发票税额”费率填报税率需与各单位最终提供的增值税发票票面显示税率保持一致。
A21: 4、 | B21: 关于区采清单、模拟清单与后续实际单项目合同的关系： 区采清单：为全费用固定综合单价清单，后续双方签订战略合同、后续实际单项目合同时进行使用，作为战略合同重要的组成部分。 模拟清单：招标方提供的模拟清单内工程量是招标方根据以往实际工程选取的模拟工程量，此模拟工程量作为投标报价确定的共同的基础，仅供招标方做评标参考，是为不能作为最终结算与支付的依据，也不作为招标方与中标方签订合同依据，双方均不需对该工程量负责。 后续实际单项目合同：战略合同签订后，实际工程计量和工程价款的支付应遵循合同条款的约定和技术标准和要求的有关规定。实际工程量由承包人按工程量清单中规定的计算规则依据项目实际图纸等进行计算；综合单价以区采清单为准；实际工程价款按工程量清单中所报的单价和总价及合同中另有规定的发包人或监理人同意的单价和总价计算支付额。
A22: 5、 | B22: 关于“本清单执行期”的说明：本清单执行期与本清单对应的区域采购战略协议中约定的“本区采协议合作期限”保持一致，并满足区采合作协议中对于“若在前述区采期限内，甲方调整发展方向或市场发生变化时，甲方有权随时解除本协议，乙方不得因此提出任何异议或向甲方主张任何违约责任”相关约定，即对应的区采协议解除后，本清单执行期自动修正为原约定起始时间至解除区采协议时终止时间。实际单项目在选用本区采清单签订项目施工合同时，其时间需满足上述关于本清单执行期中起止时间的约定。

Sheet 封面
A3: 玖华台邸项目全过程造价咨询业务补充协议一
A9: 清单计价表
A14: 咨询单位: | C14: (单位盖章)
A15: 法定代表人: | C15: (签字或盖章)
A16: 编 制 人: | C16: (签字或盖章)
A17: 编 制 时 间:

Sheet 编制说明
A1: 玖华台邸项目全过程造价咨询业务补充协议一
A2: 编制、填报说明
A4: 一、术语解释:
A5: 1、 | B5: 本清单中“以下” 含本身，“以上”不含本身
A7: 二、清单项适用范围说明：
A8: 1、 | B8: 本清单价格适用于玖华台邸项目全过程造价咨询服务补充协议。
A10: 三、计算规则：
A11: 1、 | B11: 采用工程量清单计价方式，各子目计算规则详清单。
A13: 四、特别说明、填报说明
A14: 1、 | B14: 小高层、高层、超高层、办公楼、独立商业、除别墅外下方裙房商业（均不分层高、层数）相同楼栋及别墅（不分产品类型）、花园洋房、叠拼、学校、幼儿园、别墅下裙房商业、会所、门房、岗亭相同楼栋主要是针对具有多栋相同楼栋的建筑物时，其中一栋楼按基本费单价（第1项或第3项）计算咨询费，其它楼栋按相同楼栋单价（第2项或第4项）计算咨询费，面积仍按该楼栋的施工图预算的建筑面积（同总包单位计算措施费的建筑面积一致）计算。相同楼栋判断标准：按建筑图纸是否相同进行判断（按楼栋编号命名是否在同一张图纸上，如有局部差异仍按相同楼栋执行），如高层1#楼与高层2#楼3~26层建筑图相同，则1#楼3~26层咨询费按以上清单第1项进行计算，2#楼3~26层按以上清单第2项相同楼栋单价计算咨询费。洋房、别墅相同楼栋均参照此例计算咨询费。
A15: 2、 | B15: 车库归属按为谁服务进行判断，车库为别墅服务再按别墅区车库、为高层服务则按高层区车库计算咨询费用。
A16: 3、 | B16: 咨询单位提供的发票为“增值税专用发票”，且需符合咨询合同（指建设单位与咨询单位针对其具体实施项目所签订的咨询合同）中的相关要求。
A17: 4、 | B17: 施工图预算中“二次设计内容（或分包工程）第8~20项”涉及相同户型、相同楼栋、相同设计等相同内容的只计算相同内容的一个部分的咨询费，但出具的咨询报告应包含所有的“二次设计内容（或分包工程）”的内容。（例如：2#楼公共部位装修共计26层，该26层装修均相同，计算咨询费时，只计算首层的公共部位装修的咨询费，但咨询报告应包括首层至26层的总造价。）
A18: 5、 | B18: 本清单中“增值税发票税额”费率填报税率需与咨询单位最终提供的增值税发票票面显示税率保持一致。
A19: 6、 | B19: 由于设计变更等甲方的原因造成的返工，无论变更一次或多次均补偿一次，且返工的面积需超过本次委托单项工程面积的60%以上。 4.1 施工图预算中以上清单第1~6项由于甲方的原因造成已计算完成的工程量作废而进行的返工、补偿按相应的业态的固定包干单价× 40% ×返工的面积（报百分比）。 4.2 施工图预算中以上清单第7项由于甲方的原因造成已计算完成的工程量作废而进行的返工、补偿按相应的返工范围的总造价× 40% ×合同约定千分比（报百分比）。
A20: 7、 | B20: 本合作协议中约定的价格为甲方与乙方签订具体项目《玖华台邸项目工程造价咨询合同》或《全过程造价咨询合同》的定价依据，该区采协议的附件报价清单体系应被认为乙方理解并接受该价款的合理性以及风险，该单价在本协议确定的合作期内不因市场变化而进行任何调整。

Sheet 表3 汇总表
A1: 玖华台邸项目全过程造价咨询业务补充协议一
A2: 费用汇总表
G3: 勿删！金额检查列！
A4: 序号 | B4: 项目名称 | C4: 新项目合价 | E4: 备注 | G4: 老项目合价 | I4: 新项目合价
C5: 合价1 | D5: 合价2 | G5: 合价1 | H5: 合价2 | I5: 合价3 | J5: 合价4
C6: 不含增值税 | D6: 含增值税 | G6: 不含增值税 | H6: 含增值税 | I6: 不含增值税 | J6: 含增值税
I7: =IF(ISBLANK($B7)=TRUE,"",IF(VLOOKUP($B7,#REF!,6,FALSE)=C7,"OK","NOT OK")) | J7: =IF(ISBLANK($B7)=TRUE,"",IF(VLOOKUP($B7,#REF!,7,FALSE)=D7,"OK","NOT OK"))
A8: 一 | B8: 总包预结算 | C8: =D8/1.06 -> #REF! | D8: =#REF! -> #REF! | G8: #N/A | H8: #N/A | I8: =IF(ISBLANK($B8)=TRUE,"",IF(VLOOKUP($B8,#REF!,6,FALSE)=C8,"OK","NOT OK")) -> #REF! | J8: =IF(ISBLANK($B8)=TRUE,"",IF(VLOOKUP($B8,#REF!,7,FALSE)=D8,"OK","NOT OK")) -> #REF!
I9: =IF(ISBLANK($B9)=TRUE,"",IF(VLOOKUP($B9,#REF!,6,FALSE)=C9,"OK","NOT OK")) | J9: =IF(ISBLANK($B9)=TRUE,"",IF(VLOOKUP($B9,#REF!,7,FALSE)=D9,"OK","NOT OK"))
A10: 二 | B10: 延期增加的咨询费 | C10: =D10/1.06 -> #REF! | D10: =#REF! -> #REF! | G10: #N/A | H10: #N/A | I10: =IF(ISBLANK($B10)=TRUE,"",IF(VLOOKUP($B10,#REF!,6,FALSE)=C10,"OK","NOT OK")) -> #REF! | J10: =IF(ISBLANK($B10)=TRUE,"",IF(VLOOKUP($B10,#REF!,7,FALSE)=D10,"OK","NOT OK")) -> #REF!
I11: =IF(ISBLANK($B11)=TRUE,"",IF(VLOOKUP($B11,#REF!,6,FALSE)=C11,"OK","NOT OK")) | J11: =IF(ISBLANK($B11)=TRUE,"",IF(VLOOKUP($B11,#REF!,7,FALSE)=D11,"OK","NOT OK"))
A12: 合计 | B12: 分部分项工程造价小计： | C12: =SUBTOTAL(9,C7:C11) -> #REF! | D12: =SUBTOTAL(9,D7:D11) -> #REF! | G12: #REF! | H12: #REF! | I12: =IF(ISBLANK($B12)=TRUE,"",IF(VLOOKUP($B12,#REF!,6,FALSE)=C12,"OK","NOT OK")) -> #REF! | J12: =IF(ISBLANK($B12)=TRUE,"",IF(VLOOKUP($B12,#REF!,7,FALSE)=D12,"OK","NOT OK")) -> #REF!

Sheet 计价表（模板）
A1: XXXX项目咨询费补充费用计价明细
A2: 一 | B2: 总包预结算 | C2: 计算规则 | D2: 单价（元/㎡） | E2: 建筑面积 （㎡） | F2: 合计金额 | G2: 备注
B3: 方案1
A4: 1 | B4: 原单位撤场结算费用 | C4: 按总包已完成主体结构建筑面积计算 | D4: 1 | E4: =工程量计算式!D23 -> 122415.85 | F4: =ROUND(D4*E4,2) -> 122415.85
A5: 2 | B5: 新单位施工图预算费用 | C5: 按总建筑面积计算 | D5: 2.2 | E5: =工程量计算式!C23 -> 199065.48 | F5: =ROUND(D5*E5,2) -> 437944.06
F6: =SUM(F4:F5) -> 560359.91
B7: 方案2
A8: 1 | B8: 施工图预算 （独商除外） | C8: 按总建筑面积均返工*40% | D8: =+'区采 表4.1 综合单价清单'!H12 -> 2.47722 | E8: =+'区采 表4.1 综合单价清单'!F12 -> 197402.06 | F8: =ROUND(D8*E8*0.4,2) -> 195603.33
A9: 2 | B9: 施工图预算 （独商） | C9: 按总建筑面积均返工*40% | D9: =+'区采 表4.1 综合单价清单'!H18 -> 4.95444 | E9: =+'区采 表4.1 综合单价清单'!F18 -> 1663.42 | F9: =ROUND(D9*E9*0.4,2) -> 3296.53
F10: =SUM(F8:F9) -> 198899.86
B11: 方案3
A12: 1 | B12: 施工图预算 （独商除外） | C12: 按总建筑面积均返工*100% | D12: =+'区采 表4.1 综合单价清单'!H12 -> 2.47722 | E12: =+E8 -> 197402.06 | F12: =ROUND(D12*E12,2) -> 489008.33
A13: 2 | B13: 施工图预算 （独商） | C13: 按总建筑面积均返工*100% | D13: =+'区采 表4.1 综合单价清单'!H18 -> 4.95444 | E13: =+E9 -> 1663.42 | F13: =ROUND(D13*E13,2) -> 8241.31
F14: =SUM(F12:F13) -> 497249.64
A15: 二 | B15: 延期增加的咨询费 | C15: 计算规则 | D15: 费用单价（元/月） | E15: 延期时间（月） | F15: 费用合价（元）
A16: 1 | B16: 施工过程中造价控制月度咨询费 | C16: 按月计算 （满算延期） | D16: =2.5/19.07*199065.48 -> 26096.681 | E16: 25 | F16: =ROUND(D16*E16,2) -> 652417.02 | G16: 原总包合同中约定，竣工备案时间是2018年12月30日，新总包签订的合同约定竣工备案时间是2021年4月30日。考虑竣工备案后有3个月的结算期，延期时间从2019年4月起算，延期时间暂按25个月，最终以实际延期时间为准
A17: 2 | B17: 施工过程中造价控制月度咨询费 | C17: 按月计算 （三建撤场延期*合同单价+其余超期*10000） | D17: 26096.68/10000 | E17: 6+19 | F17: =6*D16+19*10000 -> 346580.08
A18: 3 | B18: 施工过程中造价控制月度咨询费 | C18: 按月计算 （19月延期+6月超期） | D18: 26096.68/10000 | E18: 19+6 | F18: =19*D16+6*10000 -> 555836.93
A20: 备注：以上表格中6个月延期为因原单位撤场导致，19个月超期为因其他因素导致。
F21: =+F6+F16 -> 1212776.9

Sheet 工程量计算式
A1: XXX项目建筑面积统计
A2: 序号 | B2: 楼栋 | C2: 合同建筑面积 | D2: 已完成建筑面积 | E2: 未完成建筑面积 | F2: 备注
A3: 1 | B3: 1#裙房商业 | C3: 629.69 | D3: =C3 -> 629.69 | E3: =C3-D3 -> 0
A4: 2 | B4: 1#高层住宅 | C4: 15057.24 | D4: =134.19+512.73*27 -> 13977.9 | E4: =C4-D4 -> 1079.34 | F4: 28层主体完成
A5: 3 | B5: 2#裙房商业 | C5: 2655.32 | D5: =C5 -> 2655.32 | E5: =C5-D5 -> 0
A6: 4 | B6: 2#返迁办公楼 | C6: 10981.38 | D6: =C6 -> 10981.38 | E6: =C6-D6 -> 0
A7: 5 | B7: 2#自持公寓 | C7: 10051.72 | D7: =C7-101.24 -> 9950.48 | E7: =C7-D7 -> 101.24 | F7: 屋面层未完成
A8: 6 | B8: 3#裙房商业 | C8: 1284.33 | D8: =C8 -> 1284.33 | E8: =C8-D8 -> 0
A9: 7 | B9: 3#LOFT | C9: 45432.46 | D9: =302.22+1663.34*17 -> 28579 | E9: =C9-D9 -> 16853.46 | F9: 18层主体完成
A10: 8 | B10: 4#裙房商业 | C10: 515.62 | D10: 0 | E10: =C10-D10 -> 515.62
A11: 9 | B11: 4#高层住宅 | C11: 13599 | D11: 0 | E11: =C11-D11 -> 13599
A12: 10 | B12: 5#-1裙房商业 | C12: 422.93 | D12: 0 | E12: =C12-D12 -> 422.93
A13: 11 | B13: 5#-1高层住宅 | C13: 13597.21 | D13: 0 | E13: =C13-D13 -> 13597.21
A14: 12 | B14: 5#-2裙房商业 | C14: 654.13 | D14: 0 | E14: =C14-D14 -> 654.13
A15: 13 | B15: 5#-2返迁住宅 | C15: 2472.26 | D15: 0 | E15: =C15-D15 -> 2472.26
A16: 14 | B16: 6#裙房商业 | C16: 409.87 | D16: 0 | E16: =C16-D16 -> 409.87
A17: 15 | B17: 6#高层住宅 | C17: 13597.46 | D17: 0 | E17: =C17-D17 -> 13597.46
A18: 16 | B18: 7#裙房商业 | C18: 1054.32 | D18: 0 | E18: =C18-D18 -> 1054.32
A19: 17 | B19: 8#裙房商业 | C19: 480.61 | D19: =C19 -> 480.61 | E19: =C19-D19 -> 0
A20: 18 | B20: 8#高层住宅 | C20: 15425.85 | D20: =135.41+383.58+512.17*11 -> 6152.86 | E20: =C20-D20 -> 9272.99 | F20: 13层主体结构完成
A21: 19 | B21: 9#独立商业 | C21: 1663.42 | D21: =C21 -> 1663.42 | E21: =C21-D21 -> 0
A22: 20 | B22: 地下室车库 | C22: 49080.66 | D22: =C22-E22 -> 46060.86 | E22: =1509.9*2 -> 3019.8 | F22: 5#楼南侧车库-1层、-2层未施工
A23: 21 | B23: 合计 | C23: =SUM(C3:C22) -> 199065.48 | D23: =SUM(D3:D22) -> 122415.85 | E23: =SUM(E3:E22) -> 76649.63
